bison_db-0.1.2.dist-info/METADATA
bison_db-0.1.2.dist-info/WHEEL
bison.libs/libgcc_s-1e52349c.so.1
bison/__init__.py
bison/bison.pypy39-pp73-x86_64-linux-gnu.so
bison_db-0.1.2.dist-info/RECORD
