Metadata-Version: 2.3
Name: bison-db
Version: 0.1.2
Classifier: Programming Language :: Rust
Classifier: Programming Language :: Python :: Implementation :: CPython
Classifier: Programming Language :: Python :: Implementation :: PyPy
Summary: Bison is a fast, lightweight NoSQL database, written in Rust with seamless Python bindings.
Author: Manuel Concepcion Brito
License: MIT
Requires-Python: >=3.8
